Metadata-Version: 2.1
Name: jses-environment
Version: 0.2
Summary: Esse pacote cria um ambiente no Google Colab para quem deseja trabalhar com Spark e ElasticSearch.
Home-page: https://github.com/joseaugustoduarte/jses_environment.git
Author: José Augusto Duarte
Author-email: joseaugustoduarte@gmail.com
License: MIT License
Platform: UNKNOWN
